[
    { "label": "Queimada", "ndvi": -0.1},
    { "label": "Queimada", "ndvi": -0.2 },
    { "label": "Queimada", "ndvi": -0.3 },
    { "label": "Queimada", "ndvi": -0.4 },
    { "label": "Queimada", "ndvi": -0.5 },
    { "label": "Queimada", "ndvi": -0.6 },
    { "label": "Queimada", "ndvi": -0.7 },
    { "label": "Queimada", "ndvi": -0.8 },
    { "label": "Queimada", "ndvi": -0.9 },
    { "label": "Queimada", "ndvi": -1.0 },
    { "label": "Queimada", "ndvi": -0.95 },
    { "label": "Queimada", "ndvi": -0.85 },
    { "label": "Queimada", "ndvi": -0.75 },
    { "label": "Queimada", "ndvi": -0.65 },
    { "label": "Queimada", "ndvi": -0.55 },
    { "label": "Queimada",  "ndvi": -0.45},
    { "label": "Queimada",  "ndvi": -0.35},
    { "label": "Queimada",  "ndvi": -0.25},
    { "label": "Queimada",  "ndvi": -0.15},
    { "label": "Queimada",  "ndvi": -0.05},
    { "label": "Queimada",  "ndvi": 0.0},
    { "label": "Vegetacao",  "ndvi": 0.0},
    { "label": "Vegetacao",  "ndvi": 0.05},
    { "label": "Vegetacao",  "ndvi": 0.1},
    { "label": "Vegetacao",  "ndvi": 0.15},
    { "label": "Vegetacao",  "ndvi": 0.2},
    { "label": "Vegetacao",  "ndvi": 0.25},
    { "label": "Vegetacao",  "ndvi": 0.3},
    { "label": "Vegetacao",  "ndvi": 0.35},
    { "label": "Vegetacao",  "ndvi": 0.4},
    { "label": "Vegetacao",  "ndvi": 0.45},
    { "label": "Vegetacao",  "ndvi": 0.1},
    { "label": "Vegetacao", "ndvi": 0.2},
    { "label": "Vegetacao",  "ndvi": 0.3},
    { "label": "Vegetacao",  "ndvi": 0.4},
    { "label": "Vegetacao",  "ndvi": 0.5},
    { "label": "Vegetacao", "ndvi": 0.6 },
    { "label": "Vegetacao", "ndvi": 0.7 },
    { "label": "Vegetacao", "ndvi": 0.8 },
    { "label": "Vegetacao", "ndvi": 0.9}
  ]